{
  "sheet_name_mappings": {
    "comment": "Map quantity data sheet names to template config sheet names",
    "mappings": {
      "INV": "Invoice",
      "INVOICE": "Invoice",
      "Invoice": "Invoice",
      "PAK": "Packing list",
      "PACKING": "Packing list",
      "PACKING LIST": "Packing list",
      "Packing list": "Packing list",
      "CON": "Contract",
      "CONTRACT": "Contract",
      "Contract": "Contract",
      "INVOICE_NEW": "Invoice"
    }
  },
  "header_text_mappings": {
    "comment": "Map header texts from quantity data to column IDs in template",
    "mappings": {
      "Mark & Nº": "col_static",
      "Mark & N°": "col_static",
      "MARK & NOTE": "col_static",
      "Mark & Note": "col_static",
      "P.O Nº": "col_po",
      "P.O. Nº": "col_po",
      "P.O N°": "col_po",
      "P.O. N°": "col_po",
      "P.O. NO.": "col_po",
      "P.O": "col_po",
      "ITEM Nº": "col_item",
      "ITEM N°": "col_item",
      "HL ITEM": "col_item",
      "ITEM": "col_item",
      "Description": "col_desc",
      "DESCRIPTION": "col_desc",
      "Cargo Description": "col_po",
      "Cargo Descprition": "col_po",
      "Quantity": "col_qty_sf",
      "QUANTITY": "col_qty_sf",
      "Quantity\n(SF)": "col_qty_sf",
      "QUANTITY  (SQFT)": "col_qty_sf",
      "Qty": "col_qty_sf",
      "Unit price": "col_unit_price",
      "Unit price (USD)": "col_unit_price",
      "Unit price\n(USD)": "col_unit_price",
      "Unit Price(USD)": "col_unit_price",
      "UNIT PRICE(USD)": "col_unit_price",
      "FCA": "col_unit_price",
      "FCA\nSVAY RIENG": "col_unit_price",
      "Amount": "col_amount",
      "Amount (USD)": "col_amount",
      "Amount(USD)": "col_amount",
      "AMOUNT(USD)": "col_amount",
      "Total value(USD)": "col_amount",
      "N.W (kgs)": "col_net",
      "NW(KGS)": "col_net",
      "Net Weight": "col_net",
      "G.W (kgs)": "col_gross",
      "GW(KGS)": "col_gross",
      "Gross Weight": "col_gross",
      "CBM": "col_cbm",
      "(CBM)": "col_cbm",
      "PCS": "col_qty_pcs",
      "SF": "col_qty_sf",
      "No.": "col_no",
      "Pallet\nNO.": "col_pallet",
      "REMARKS": "col_remarks",
      "HS CODE": "col_hs_code",
      "TOTAL PRICE": "col_amount",
      "TEST HEADER": "col_test",
      "Name of\\nCormodity": "col_item",
      "Unit Price\\n(USD)": "col_unit_price",
      "Total value\\n(USD)": "col_amount",
      "PALLET\\nNO.": "col_pallet",
      "Name of\nCormodity": "col_item",
      "Unit Price\n(USD)": "col_unit_price",
      "Amount(USD)asdfasdfasdfasdfasdfasdf": "col_amount",
      "NO": "col_no",
      "Name of  \n Cormodity": "col_item",
      "Quantity（SF）": "col_qty_sf",
      "Unit Price  (USD)": "col_unit_price",
      "Quantity               (SF)": "col_qty_sf",
      "Unite price   (USD)": "col_unit_price",
      "G.W(kgs)": "col_gross"
    }
  },
  "fallback_strategies": {
    "comment": "Configuration for handling unrecognized headers and sheets",
    "case_insensitive_matching": true,
    "partial_matching_threshold": 0.7,
    "log_unrecognized_items": true,
    "create_suggestions": true
  }
}